adb_mysql_mcp_server/__init__.py
adb_mysql_mcp_server/server.py
adb_mysql_mcp_server-1.0.0.dist-info/METADATA
adb_mysql_mcp_server-1.0.0.dist-info/WHEEL
adb_mysql_mcp_server-1.0.0.dist-info/entry_points.txt
adb_mysql_mcp_server-1.0.0.dist-info/licenses/LICENSE
adb_mysql_mcp_server-1.0.0.dist-info/RECORD
