Metadata-Version: 2.4
Name: adb-mysql-mcp-server
Version: 1.0.0
Summary: An offical mcp server for Adb MySQL of Alibaba Cloud
Author-email: lipandong <pandong.lpd@alibaba-inc.com>
License-File: LICENSE
Requires-Python: >=3.13
Requires-Dist: mcp[cli]>=1.5.0
Requires-Dist: pymysql>=1.1.1
